src/__init__.py
src/constant/__init__.py
src/constant/colors.py
src/constant/doms.py
src/constant/pairs.py
src/core/__init__.py
src/core/curses.py
src/core/pycurses.py
src/core/window.py
src/cprint/__init__.py
src/cprint/code.py
src/elements/__init__.py
src/elements/dom.py
src/elements/section.py
src/elements/span.py
src/elements/window.py
src/themes/__init__.py
src/themes/theme.py
src/themes/theme_github.py
src/themes/theme_sky.py
src/themes/theme_solarized_dark.py
python_terminal-1.0.dist-info/METADATA
python_terminal-1.0.dist-info/WHEEL
python_terminal-1.0.dist-info/top_level.txt
python_terminal-1.0.dist-info/RECORD
