Metadata-Version: 2.1
Name: python-terminal
Version: 1.0
Summary: Quickly build a terminal project
Home-page: https://github.com/zhcshine/pyterminal
Author: zhuohc
Author-email: zhcshine@gmail.com
License: MIT
Keywords: pyterminal,terminal,终端
Platform: UNKNOWN
Classifier: Programming Language :: Python :: 3.4
Classifier: License :: OSI Approved :: MIT License
Classifier: Operating System :: OS Independent
Requires-Python: >=3.4.0
Requires-Dist: pyterminal (==1.0)
